FileCopy_01/Robin.Files.FileCopy_01-Python.robin-impinfo
FileCopy_01/__init__.py
FileCopy_01/action.py
FileCopy_01/exceptions.py
FileCopy_01/common/__init__.py
FileCopy_01/common/mixins.py
FileCopy_01/common/validators.py
Robin.Files.FileCopy_01_Python-1.5.2.dist-info/METADATA
Robin.Files.FileCopy_01_Python-1.5.2.dist-info/WHEEL
Robin.Files.FileCopy_01_Python-1.5.2.dist-info/top_level.txt
Robin.Files.FileCopy_01_Python-1.5.2.dist-info/RECORD
